dacite/__init__.py
dacite/cache.py
dacite/config.py
dacite/core.py
dacite/data.py
dacite/dataclasses.py
dacite/exceptions.py
dacite/frozen_dict.py
dacite/py.typed
dacite/types.py
dacite_retrofit-1.0.1.dist-info/LICENSE
dacite_retrofit-1.0.1.dist-info/METADATA
dacite_retrofit-1.0.1.dist-info/WHEEL
dacite_retrofit-1.0.1.dist-info/RECORD
