Metadata-Version: 2.1
Name: dacite-retrofit
Version: 1.0.1
Summary: A dacite fork with support for PEP 585/604 typehints in 3.8+.
License: MIT
Author: trag1c
Author-email: trag1cdev@yahoo.com
Requires-Python: >=3.8,<4.0
Classifier: License :: OSI Approved :: MIT License
Classifier: Programming Language :: Python :: 3
Classifier: Programming Language :: Python :: 3.8
Classifier: Programming Language :: Python :: 3.9
Classifier: Programming Language :: Python :: 3.10
Classifier: Programming Language :: Python :: 3.11
Requires-Dist: future-typing (>=0.4.1,<0.5.0)
